odoo/addons/l10n_br_cte_spec/README.rst
odoo/addons/l10n_br_cte_spec/__init__.py
odoo/addons/l10n_br_cte_spec/__manifest__.py
odoo/addons/l10n_br_cte_spec/i18n/l10n_br_cte_spec.pot
odoo/addons/l10n_br_cte_spec/i18n/pt_BR.po
odoo/addons/l10n_br_cte_spec/models/__init__.py
odoo/addons/l10n_br_cte_spec/models/spec_mixin.py
odoo/addons/l10n_br_cte_spec/models/v4_0/__init__.py
odoo/addons/l10n_br_cte_spec/models/v4_0/cte_modal_aereo_v4_00.py
odoo/addons/l10n_br_cte_spec/models/v4_0/cte_modal_aquaviario_v4_00.py
odoo/addons/l10n_br_cte_spec/models/v4_0/cte_modal_dutoviario_v4_00.py
odoo/addons/l10n_br_cte_spec/models/v4_0/cte_modal_ferroviario_v4_00.py
odoo/addons/l10n_br_cte_spec/models/v4_0/cte_modal_rodoviario_os_v4_00.py
odoo/addons/l10n_br_cte_spec/models/v4_0/cte_modal_rodoviario_v4_00.py
odoo/addons/l10n_br_cte_spec/models/v4_0/cte_multi_modal_v4_00.py
odoo/addons/l10n_br_cte_spec/models/v4_0/cte_tipos_basico_v4_00.py
odoo/addons/l10n_br_cte_spec/models/v4_0/evento_cte_tipos_basico_v4_00.py
odoo/addons/l10n_br_cte_spec/models/v4_0/tipos_geral_cte_v4_00.py
odoo/addons/l10n_br_cte_spec/readme/CONTRIBUTORS.rst
odoo/addons/l10n_br_cte_spec/readme/DESCRIPTION.rst
odoo/addons/l10n_br_cte_spec/static/description/icon.png
odoo/addons/l10n_br_cte_spec/static/description/index.html
odoo/addons/l10n_br_cte_spec/tests/__init__.py
odoo/addons/l10n_br_cte_spec/tests/test_cte_import.py
odoo14_addon_l10n_br_cte_spec-14.0.2.0.1.dev4.dist-info/METADATA
odoo14_addon_l10n_br_cte_spec-14.0.2.0.1.dev4.dist-info/WHEEL
odoo14_addon_l10n_br_cte_spec-14.0.2.0.1.dev4.dist-info/top_level.txt
odoo14_addon_l10n_br_cte_spec-14.0.2.0.1.dev4.dist-info/RECORD
